tableland/__init__.py
tableland/__main__.py
tableland/abi.json
tableland/database.py
tableland/helpers.py
tableland/types.py
tableland-0.0.2.dist-info/LICENSE
tableland-0.0.2.dist-info/LICENSE-APACHE
tableland-0.0.2.dist-info/METADATA
tableland-0.0.2.dist-info/WHEEL
tableland-0.0.2.dist-info/RECORD
