Metadata-Version: 2.1
Name: tableland
Version: 0.0.2
Summary: A minimal Tableland Python SDK for creating, writing, and reading onchain tables
License: MIT AND Apache-2.0
Author: Dan Buchholz
Author-email: dbuchholz30@gmail.com
Requires-Python: >=3.11,<4.0
Classifier: License :: Other/Proprietary License
Classifier: Programming Language :: Python :: 3
Classifier: Programming Language :: Python :: 3.11
Classifier: Programming Language :: Python :: 3.12
Requires-Dist: requests (>=2.31.0,<3.0.0)
Requires-Dist: sqlglot (>=23.6.3,<24.0.0)
Requires-Dist: web3 (>=6.16.0,<7.0.0)
